pysenz/__init__.py
pysenz/account.py
pysenz/api.py
pysenz/auth.py
pysenz/py.typed
pysenz/thermostat.py
pysenz/typing.py
pysenz-1.0.1b1.dist-info/licenses/COPYING
pysenz-1.0.1b1.dist-info/METADATA
pysenz-1.0.1b1.dist-info/WHEEL
pysenz-1.0.1b1.dist-info/top_level.txt
pysenz-1.0.1b1.dist-info/RECORD
