Metadata-Version: 2.4
Name: pysenz
Version: 1.0.1b1
Summary: Async Typed Python package for the Chemelex (nVent) RAYCHEM SENZ RestAPI
Home-page: https://github.com/nordicopen/pysenz
Author: Åke Strandberg
Author-email: ake@strandberg.eu
Maintainer: Åke Strandberg
Maintainer-email: ake@strandberg.eu
License: LGPLv3+
Project-URL: Say Thanks!, https://saythanks.io/to/milan.meulemans@live.be
Project-URL: Bug Tracker, https://github.com/nordicopen/pysenz/issues
Project-URL: Source Code, https://github.com/nordicopen/pysenz
Project-URL: Documentation, https://github.com/nordicopen/pysenz/blob/main/README.md
Keywords: nvent,raychem,senz,wifi,api,restapi,oauth2,chemelex
Classifier: Programming Language :: Python :: 3
Classifier: License :: OSI Approved :: GNU Lesser General Public License v3 or later (LGPLv3+)
Classifier: Operating System :: OS Independent
Requires-Python: >=3.8
License-File: COPYING
Requires-Dist: httpx
Requires-Dist: authlib
Dynamic: license-file
